{"skeleton":{"hash":"fR6PJ3VuAG822ALvPSqjiYCi7O0","spine":"3.7.92","width":0,"height":0,"images":"","audio":"Z:/6.特效/1.角色特效/1.英雄特效/6.优化英雄/乔丹/E_qiaodan"},"bones":[{"name":"root"},{"name":"atk_bao","parent":"root"},{"name":"atk_di","parent":"root"},{"name":"atk_zidan","parent":"root"},{"name":"atk_qiu","parent":"root"},{"name":"atk_quan","parent":"root"},{"name":"skill1_bang","parent":"root","y":-12.8},{"name":"skill1_bao","parent":"root"},{"name":"skill1_kuang","parent":"root"},{"name":"skill3_di","parent":"root"},{"name":"skill3_huo","parent":"root"},{"name":"com","parent":"root"},{"name":"images/skill4/dahuo0001","parent":"root","length":378.18,"rotation":90.73,"x":-1.8,"y":335.19},{"name":"images/skill4/dadi","parent":"root","length":200.91,"rotation":85.85,"x":101.63,"y":454.78}],"slots":[{"name":"atk_di","bone":"atk_di"},{"name":"atk_quan","bone":"atk_quan","blend":"additive"},{"name":"atk_bao","bone":"atk_bao","blend":"additive"},{"name":"atk_qiu","bone":"atk_qiu"},{"name":"atk_zidan","bone":"atk_zidan","blend":"additive"},{"name":"skill1_kuang","bone":"skill1_kuang"},{"name":"skill1_bao","bone":"skill1_bao","blend":"additive"},{"name":"skill1_bang","bone":"skill1_bang"},{"name":"skill3_di","bone":"skill3_di"},{"name":"skill3_huo","bone":"skill3_huo","blend":"additive"},{"name":"com/com_dilie_001","bone":"com"},{"name":"images/skill4/dadi","bone":"images/skill4/dadi"},{"name":"images/skill4/dahuo0001","bone":"images/skill4/dahuo0001","blend":"additive"}],"skins":{"default":{"atk_bao":{"images/atk/bao0001":{"width":300,"height":280},"images/atk/bao0003":{"width":300,"height":280},"images/atk/bao0005":{"width":300,"height":280},"images/atk/bao0007":{"width":300,"height":280},"images/atk/bao0009":{"width":300,"height":280},"images/atk/bao0011":{"width":300,"height":280},"images/atk/bao0013":{"width":300,"height":280},"images/atk/bao0015":{"width":300,"height":280},"images/atk/bao0017":{"width":300,"height":280},"images/atk/bao0019":{"width":300,"height":280},"images/atk/bao0021":{"width":300,"height":280},"images/atk/bao0023":{"width":300,"height":280},"images/atk/bao0025":{"width":300,"height":280},"images/atk/bao0027":{"width":300,"height":280},"images/atk/bao0028":{"width":300,"height":280}},"atk_di":{"images/atk/di":{"width":290,"height":260}},"atk_qiu":{"images/atk/qiu":{"x":0.5,"y":0.5,"width":55,"height":55}},"atk_quan":{"images/atk/quan0001":{"width":250,"height":200},"images/atk/quan0002":{"width":250,"height":200},"images/atk/quan0003":{"width":250,"height":200},"images/atk/quan0005":{"width":250,"height":200},"images/atk/quan0007":{"width":250,"height":200},"images/atk/quan0009":{"width":250,"height":200},"images/atk/quan0011":{"width":250,"height":200},"images/atk/quan0013":{"width":250,"height":200},"images/atk/quan0015":{"width":250,"height":200},"images/atk/quan0017":{"width":250,"height":200},"images/atk/quan0019":{"width":250,"height":200},"images/atk/quan0021":{"width":250,"height":200},"images/atk/quan0022":{"width":250,"height":200}},"atk_zidan":{"images/atk/feixing0001":{"x":0.5,"y":0.5,"width":175,"height":85},"images/atk/feixing0002":{"x":0.5,"y":0.5,"width":175,"height":85},"images/atk/feixing0003":{"x":0.5,"y":0.5,"width":175,"height":85},"images/atk/feixing0004":{"x":0.5,"y":0.5,"width":175,"height":85},"images/atk/feixing0005":{"x":0.5,"y":0.5,"width":175,"height":85},"images/atk/feixing0006":{"x":0.5,"y":0.5,"width":175,"height":85}},"com/com_dilie_001":{"images/com/com_dilie_001":{"width":204,"height":64},"images/com/com_dilie_002":{"width":246,"height":78},"images/com/com_dilie_003":{"width":326,"height":104},"images/com/com_dilie_004":{"width":332,"height":132},"images/com/com_dilie_005":{"width":332,"height":138},"images/com/com_dilie_006":{"width":298,"height":80}},"images/skill4/dadi":{"images/skill4/dadi":{"x":37.07,"y":2.69,"rotation":-85.85,"width":264,"height":224}},"images/skill4/dahuo0001":{"images/skill4/dahuo0001":{"y":0.5,"width":264,"height":224},"images/skill4/dahuo0002":{"y":0.5,"width":264,"height":224},"images/skill4/dahuo0003":{"y":0.5,"width":264,"height":224},"images/skill4/dahuo0004":{"y":0.5,"width":264,"height":224},"images/skill4/dahuo0005":{"y":0.5,"width":264,"height":224},"images/skill4/dahuo0006":{"y":0.5,"width":264,"height":224},"images/skill4/dahuo0007":{"y":0.5,"width":264,"height":224},"images/skill4/dahuo0008":{"y":0.5,"width":264,"height":224},"images/skill4/dahuo0009":{"y":0.5,"width":264,"height":224},"images/skill4/dahuo0010":{"y":0.5,"width":264,"height":224},"images/skill4/dahuo0011":{"y":0.5,"width":264,"height":224},"images/skill4/dahuo0012":{"y":0.5,"width":264,"height":224},"images/skill4/dahuo0013":{"y":0.5,"width":264,"height":224},"images/skill4/dahuo0014":{"y":0.5,"width":264,"height":224},"images/skill4/dahuo0015":{"y":0.5,"width":264,"height":224},"images/skill4/dahuo0016":{"y":0.5,"width":264,"height":224},"images/skill4/dahuo0017":{"y":0.5,"width":264,"height":224},"images/skill4/dahuo0018":{"y":0.5,"width":264,"height":224},"images/skill4/dahuo0019":{"y":0.5,"width":264,"height":224},"images/skill4/dahuo0020":{"y":0.5,"width":264,"height":224},"images/skill4/dahuo0021":{"y":0.5,"width":264,"height":224},"images/skill4/dahuo0022":{"y":0.5,"width":264,"height":224},"images/skill4/dahuo0023":{"y":0.5,"width":264,"height":224},"images/skill4/dahuo0024":{"y":0.5,"width":264,"height":224},"images/skill4/dahuo0025":{"y":0.5,"width":264,"height":224},"images/skill4/dahuo0026":{"y":0.5,"width":264,"height":224},"images/skill4/dahuo0027":{"y":0.5,"width":264,"height":224}},"skill1_bang":{"images/skill1/bang":{"y":13.3,"width":370,"height":175}},"skill1_bao":{"images/skill1/bao0001":{"y":0.5,"width":320,"height":375},"images/skill1/bao0003":{"y":0.5,"width":320,"height":375},"images/skill1/bao0005":{"y":0.5,"width":320,"height":375},"images/skill1/bao0007":{"y":0.5,"width":320,"height":375},"images/skill1/bao0009":{"y":0.5,"width":320,"height":375},"images/skill1/bao0011":{"y":0.5,"width":320,"height":375},"images/skill1/bao0013":{"y":0.5,"width":320,"height":375},"images/skill1/bao0015":{"y":0.5,"width":320,"height":375},"images/skill1/bao0017":{"y":0.5,"width":320,"height":375},"images/skill1/bao0019":{"y":0.5,"width":320,"height":375},"images/skill1/bao0021":{"y":0.5,"width":320,"height":375},"images/skill1/bao0023":{"y":0.5,"width":320,"height":375},"images/skill1/bao0025":{"y":0.5,"width":320,"height":375},"images/skill1/bao0027":{"y":0.5,"width":320,"height":375},"images/skill1/bao0029":{"y":0.5,"width":320,"height":375},"images/skill1/bao0030":{"y":0.5,"width":320,"height":375}},"skill1_kuang":{"images/skill1/lankuang":{"width":280,"height":240}},"skill3_di":{"images/skill3/di":{"x":0.5,"width":125,"height":110}},"skill3_huo":{"images/skill3/huo0001":{"y":0.5,"width":80,"height":105},"images/skill3/huo0002":{"y":0.5,"width":80,"height":105},"images/skill3/huo0003":{"y":0.5,"width":80,"height":105},"images/skill3/huo0004":{"y":0.5,"width":80,"height":105},"images/skill3/huo0005":{"y":0.5,"width":80,"height":105},"images/skill3/huo0006":{"y":0.5,"width":80,"height":105},"images/skill3/huo0007":{"y":0.5,"width":80,"height":105},"images/skill3/huo0008":{"y":0.5,"width":80,"height":105},"images/skill3/huo0009":{"y":0.5,"width":80,"height":105},"images/skill3/huo0010":{"y":0.5,"width":80,"height":105},"images/skill3/huo0011":{"y":0.5,"width":80,"height":105},"images/skill3/huo0012":{"y":0.5,"width":80,"height":105},"images/skill3/huo0013":{"y":0.5,"width":80,"height":105},"images/skill3/huo0014":{"y":0.5,"width":80,"height":105},"images/skill3/huo0015":{"y":0.5,"width":80,"height":105},"images/skill3/huo0016":{"y":0.5,"width":80,"height":105},"images/skill3/huo0017":{"y":0.5,"width":80,"height":105},"images/skill3/huo0018":{"y":0.5,"width":80,"height":105},"images/skill3/huo0019":{"y":0.5,"width":80,"height":105},"images/skill3/huo0020":{"y":0.5,"width":80,"height":105},"images/skill3/huo0021":{"y":0.5,"width":80,"height":105},"images/skill3/huo0022":{"y":0.5,"width":80,"height":105},"images/skill3/huo0023":{"y":0.5,"width":80,"height":105},"images/skill3/huo0024":{"y":0.5,"width":80,"height":105},"images/skill3/huo0025":{"y":0.5,"width":80,"height":105},"images/skill3/huo0026":{"y":0.5,"width":80,"height":105},"images/skill3/huo0027":{"y":0.5,"width":80,"height":105}}}},"events":{"atk":{}},"animations":{"atk_hit":{"slots":{"atk_bao":{"attachment":[{"time":0,"name":"images/atk/bao0001"},{"time":0.0667,"name":"images/atk/bao0003"},{"time":0.1333,"name":"images/atk/bao0005"},{"time":0.2,"name":"images/atk/bao0007"},{"time":0.2667,"name":"images/atk/bao0009"},{"time":0.3333,"name":"images/atk/bao0011"},{"time":0.4,"name":"images/atk/bao0013"},{"time":0.4667,"name":"images/atk/bao0015"},{"time":0.5333,"name":"images/atk/bao0017"},{"time":0.6,"name":"images/atk/bao0019"},{"time":0.6667,"name":"images/atk/bao0021"},{"time":0.7333,"name":"images/atk/bao0023"},{"time":0.8,"name":"images/atk/bao0025"},{"time":0.8667,"name":"images/atk/bao0027"},{"time":0.9333,"name":"images/atk/bao0028"},{"time":1,"name":null}]},"atk_di":{"color":[{"time":0.4667,"color":"ffffffff"},{"time":1,"color":"ffffff00"}],"attachment":[{"time":0,"name":"images/atk/di"},{"time":1,"name":null}]},"atk_quan":{"attachment":[{"time":0.0667,"name":"images/atk/quan0001"},{"time":0.1,"name":"images/atk/quan0002"},{"time":0.1333,"name":"images/atk/quan0003"},{"time":0.2,"name":"images/atk/quan0005"},{"time":0.2667,"name":"images/atk/quan0007"},{"time":0.3333,"name":"images/atk/quan0009"},{"time":0.4,"name":"images/atk/quan0011"},{"time":0.4667,"name":"images/atk/quan0013"},{"time":0.5333,"name":"images/atk/quan0015"},{"time":0.6,"name":"images/atk/quan0017"},{"time":0.6667,"name":"images/atk/quan0019"},{"time":0.7333,"name":"images/atk/quan0021"},{"time":0.8,"name":"images/atk/quan0022"},{"time":0.8667,"name":null}]}},"bones":{"atk_bao":{"translate":[{"time":0,"x":-8.29,"y":49.06}]},"atk_di":{"translate":[{"time":0,"x":-17.3,"y":0}],"scale":[{"time":0,"x":0.618,"y":0.618},{"time":0.0667,"x":1,"y":1}]}},"events":[{"time":0,"name":"atk"}]},"atk_move":{"slots":{"atk_qiu":{"attachment":[{"time":0,"name":"images/atk/qiu"}]},"atk_zidan":{"color":[{"time":0,"color":"ffffffaa"}],"attachment":[{"time":0,"name":"images/atk/feixing0001"},{"time":0.0333,"name":"images/atk/feixing0002"},{"time":0.0667,"name":"images/atk/feixing0003"},{"time":0.1,"name":"images/atk/feixing0004"},{"time":0.1333,"name":"images/atk/feixing0005"},{"time":0.1667,"name":"images/atk/feixing0006"},{"time":0.2,"name":"images/atk/feixing0001"},{"time":0.2333,"name":"images/atk/feixing0002"},{"time":0.2667,"name":"images/atk/feixing0003"},{"time":0.3,"name":"images/atk/feixing0004"},{"time":0.3333,"name":"images/atk/feixing0005"},{"time":0.3667,"name":"images/atk/feixing0006"},{"time":0.4,"name":"images/atk/feixing0001"},{"time":0.4333,"name":"images/atk/feixing0002"},{"time":0.4667,"name":"images/atk/feixing0003"},{"time":0.5,"name":"images/atk/feixing0004"},{"time":0.5333,"name":"images/atk/feixing0005"},{"time":0.5667,"name":"images/atk/feixing0006"},{"time":0.6,"name":"images/atk/feixing0001"},{"time":0.6333,"name":"images/atk/feixing0002"},{"time":0.6667,"name":"images/atk/feixing0003"},{"time":0.7,"name":"images/atk/feixing0004"},{"time":0.7333,"name":"images/atk/feixing0005"},{"time":0.7667,"name":"images/atk/feixing0006"}]}},"bones":{"atk_qiu":{"rotate":[{"time":0,"angle":0},{"time":0.2667,"angle":120},{"time":0.5333,"angle":-120},{"time":0.7667,"angle":-17.14}]},"atk_zidan":{"translate":[{"time":0,"x":46.39,"y":0}]}}},"com_hit":{"slots":{"com/com_dilie_001":{"color":[{"time":1.5,"color":"ffffffff"},{"time":2.1667,"color":"ffffff00"}],"attachment":[{"time":0,"name":"images/com/com_dilie_001"},{"time":0.0667,"name":"images/com/com_dilie_002"},{"time":0.1333,"name":"images/com/com_dilie_003"},{"time":0.2,"name":"images/com/com_dilie_004"},{"time":0.2667,"name":"images/com/com_dilie_005"},{"time":0.3333,"name":"images/com/com_dilie_006"}]}},"bones":{"com":{"translate":[{"time":0,"x":0,"y":-15.93,"curve":"stepped"},{"time":0.3,"x":0,"y":-15.93,"curve":"stepped"},{"time":0.3333,"x":-17.52,"y":-28.67}],"scale":[{"time":0,"x":2,"y":4}]}}},"skill1_hit":{"slots":{"skill1_bang":{"color":[{"time":0.4333,"color":"ffffffff"},{"time":0.5333,"color":"ffffff37"}],"attachment":[{"time":0.0667,"name":"images/skill1/bang"},{"time":0.5333,"name":null}]},"skill1_bao":{"attachment":[{"time":0.0667,"name":"images/skill1/bao0001"},{"time":0.1333,"name":"images/skill1/bao0003"},{"time":0.2,"name":"images/skill1/bao0005"},{"time":0.2667,"name":"images/skill1/bao0007"},{"time":0.3333,"name":"images/skill1/bao0009"},{"time":0.4,"name":"images/skill1/bao0011"},{"time":0.4667,"name":"images/skill1/bao0013"},{"time":0.5333,"name":"images/skill1/bao0015"},{"time":0.6,"name":"images/skill1/bao0017"},{"time":0.6667,"name":"images/skill1/bao0019"},{"time":0.7333,"name":"images/skill1/bao0021"},{"time":0.8,"name":"images/skill1/bao0023"},{"time":0.8667,"name":"images/skill1/bao0025"},{"time":0.9333,"name":"images/skill1/bao0027"},{"time":1,"name":"images/skill1/bao0029"},{"time":1.0667,"name":"images/skill1/bao0030"},{"time":1.1333,"name":null}]},"skill1_kuang":{"color":[{"time":0.5,"color":"ffffffff"},{"time":0.6,"color":"ffffff00"}],"attachment":[{"time":0,"name":"images/skill1/lankuang"}]}},"bones":{"skill1_kuang":{"translate":[{"time":0,"x":0,"y":33.17}],"scale":[{"time":0,"x":0.532,"y":0.532},{"time":0.0667,"x":1,"y":1,"curve":"stepped"},{"time":0.5,"x":1,"y":1},{"time":0.6,"x":0.532,"y":0.532}]},"skill1_bao":{"translate":[{"time":0,"x":5.82,"y":30.26}]},"skill1_bang":{"translate":[{"time":0.0667,"x":4.66,"y":15.13},{"time":0.1333,"x":58.2,"y":81.48},{"time":0.1667,"x":67.51,"y":81.92},{"time":0.2,"x":38.25,"y":82.35},{"time":0.2333,"x":55.87,"y":81.92},{"time":0.2667,"x":58.2,"y":84.97}],"scale":[{"time":0.0667,"x":0.339,"y":0.339},{"time":0.1333,"x":1,"y":1},{"time":0.4333,"x":1.066,"y":1.066},{"time":0.5333,"x":0.438,"y":0.438}]}},"events":[{"time":0.0667,"name":"atk"}]},"skill3_hit":{"slots":{"skill3_di":{"attachment":[{"time":0,"name":"images/skill3/di"}]},"skill3_huo":{"attachment":[{"time":0,"name":"images/skill3/huo0001"},{"time":0.0333,"name":"images/skill3/huo0002"},{"time":0.0667,"name":"images/skill3/huo0003"},{"time":0.1,"name":"images/skill3/huo0004"},{"time":0.1333,"name":"images/skill3/huo0005"},{"time":0.1667,"name":"images/skill3/huo0006"},{"time":0.2,"name":"images/skill3/huo0007"},{"time":0.2333,"name":"images/skill3/huo0008"},{"time":0.2667,"name":"images/skill3/huo0009"},{"time":0.3,"name":"images/skill3/huo0010"},{"time":0.3333,"name":"images/skill3/huo0011"},{"time":0.3667,"name":"images/skill3/huo0012"},{"time":0.4,"name":"images/skill3/huo0013"},{"time":0.4333,"name":"images/skill3/huo0014"},{"time":0.4667,"name":"images/skill3/huo0015"},{"time":0.5,"name":"images/skill3/huo0016"},{"time":0.5333,"name":"images/skill3/huo0017"},{"time":0.5667,"name":"images/skill3/huo0018"},{"time":0.6,"name":"images/skill3/huo0019"},{"time":0.6333,"name":"images/skill3/huo0020"},{"time":0.6667,"name":"images/skill3/huo0021"},{"time":0.7,"name":"images/skill3/huo0022"},{"time":0.7333,"name":"images/skill3/huo0023"},{"time":0.7667,"name":"images/skill3/huo0024"},{"time":0.8,"name":"images/skill3/huo0025"},{"time":0.8333,"name":"images/skill3/huo0026"},{"time":0.8667,"name":"images/skill3/huo0027"}]}},"bones":{"skill3_di":{"translate":[{"time":0,"x":-10.51,"y":8.34}],"scale":[{"time":0,"x":1.3,"y":1.3}]},"skill3_huo":{"translate":[{"time":0,"x":0,"y":30.29}],"scale":[{"time":0,"x":1.156,"y":1.156}]}},"events":[{"time":0,"name":"atk"}]},"skill4_hit":{"slots":{"images/skill4/dadi":{"attachment":[{"time":0,"name":"images/skill4/dadi"}]},"images/skill4/dahuo0001":{"attachment":[{"time":0,"name":"images/skill4/dahuo0001"},{"time":0.0333,"name":"images/skill4/dahuo0002"},{"time":0.0667,"name":"images/skill4/dahuo0003"},{"time":0.1,"name":"images/skill4/dahuo0004"},{"time":0.1333,"name":"images/skill4/dahuo0005"},{"time":0.1667,"name":"images/skill4/dahuo0006"},{"time":0.2,"name":"images/skill4/dahuo0007"},{"time":0.2333,"name":"images/skill4/dahuo0008"},{"time":0.2667,"name":"images/skill4/dahuo0009"},{"time":0.3,"name":"images/skill4/dahuo0010"},{"time":0.3333,"name":"images/skill4/dahuo0011"},{"time":0.3667,"name":"images/skill4/dahuo0012"},{"time":0.4,"name":"images/skill4/dahuo0013"},{"time":0.4333,"name":"images/skill4/dahuo0014"},{"time":0.4667,"name":"images/skill4/dahuo0015"},{"time":0.5,"name":"images/skill4/dahuo0016"},{"time":0.5333,"name":"images/skill4/dahuo0017"},{"time":0.5667,"name":"images/skill4/dahuo0018"},{"time":0.6,"name":"images/skill4/dahuo0019"},{"time":0.6333,"name":"images/skill4/dahuo0020"},{"time":0.6667,"name":"images/skill4/dahuo0021"},{"time":0.7,"name":"images/skill4/dahuo0022"},{"time":0.7333,"name":"images/skill4/dahuo0023"},{"time":0.7667,"name":"images/skill4/dahuo0024"},{"time":0.8,"name":"images/skill4/dahuo0025"},{"time":0.8333,"name":"images/skill4/dahuo0026"},{"time":0.8667,"name":"images/skill4/dahuo0027"}]}},"bones":{"images/skill4/dahuo0001":{"rotate":[{"time":0,"angle":-90.73}],"translate":[{"time":0,"x":-2.68,"y":-326.26}]},"images/skill4/dadi":{"translate":[{"time":0,"x":-105.15,"y":-477.4}]}},"events":[{"time":0,"name":"atk"}]}}}