{"skeleton":{"hash":"FFCHzkgU9XVQ+nr/yd+c+zqE4XI","spine":"3.7.92","width":0,"height":0,"images":"","audio":""},"bones":[{"name":"root"},{"name":"quan","parent":"root"}],"slots":[{"name":"quan","bone":"quan","blend":"additive"}],"skins":{"default":{"quan":{"images/quan":{"width":128,"height":128}}}},"animations":{"stand":{"slots":{"quan":{"color":[{"time":0,"color":"ffffffff"},{"time":0.6667,"color":"ffffff2a"},{"time":1.3333,"color":"ffffffff"}],"attachment":[{"time":0,"name":"images/quan"}]}}}}}